kantan_llm/__init__.py
kantan_llm/errors.py
kantan_llm/providers.py
kantan_llm/resolver.py
kantan_llm/wrappers.py
kantan_llm/tracing/__init__.py
kantan_llm/tracing/analysis.py
kantan_llm/tracing/create.py
kantan_llm/tracing/processor_interface.py
kantan_llm/tracing/processors.py
kantan_llm/tracing/provider.py
kantan_llm/tracing/sanitize.py
kantan_llm/tracing/scope.py
kantan_llm/tracing/search.py
kantan_llm/tracing/setup.py
kantan_llm/tracing/span_data.py
kantan_llm/tracing/spans.py
kantan_llm/tracing/traces.py
kantan_llm/tracing/util.py
kantan_llm-0.1.9.dist-info/licenses/LICENSE
kantan_llm-0.1.9.dist-info/METADATA
kantan_llm-0.1.9.dist-info/WHEEL
kantan_llm-0.1.9.dist-info/top_level.txt
kantan_llm-0.1.9.dist-info/RECORD
