Metadata-Version: 2.4
Name: kantan-llm
Version: 0.1.9
Summary: Minimal LLM client getter for OpenAI Responses + OpenAI-compatible Chat Completions.
Project-URL: Repository, https://github.com/kitfactory/kantan-llm
Keywords: llm,openai,openrouter,lmstudio,ollama,gemini
Classifier: Development Status :: 3 - Alpha
Classifier: Intended Audience :: Developers
Classifier: Programming Language :: Python :: 3
Classifier: Programming Language :: Python :: 3 :: Only
Classifier: Programming Language :: Python :: 3.10
Classifier: Programming Language :: Python :: 3.11
Classifier: Programming Language :: Python :: 3.12
Classifier: Topic :: Software Development :: Libraries
Requires-Python: >=3.10
License-File: LICENSE
Requires-Dist: openai<3,>=2
Provides-Extra: dev
Requires-Dist: pytest>=7.0.0; extra == "dev"
Dynamic: license-file
